Metadata-Version: 1.1
Name: streams-plex
Version: 0.33
Summary: a little tool written in phyton to count all the active plex streams
Home-page: https://github.com/R0b95/streams_plex
Author: Strolch
Author-email: hello.circles@gmail.com
License: MIT
Download-URL: https://github.com/R0b95/streams_plex/archive/0.2.tar.gz
Keywords: plex,StreamCount,ActiveUser,ActiveStreams
Platform: UNKNOWN
Classifier: Development Status :: 4 - Beta
Classifier: Intended Audience :: Developers
Classifier: Topic :: Software Development :: Build Tools
Classifier: License :: OSI Approved :: MIT License
Classifier: Programming Language :: Python
